kubextract/__init__.py
kubextract/params/markdown.yml
kubextract/params/mnist.yml
kubextract/templates/_build-gitlab-ci.yml
kubextract/templates/_cloudbuild.yaml
kubextract/templates/_gitlab-ci.yml
kubextract/templates/_kfserving-gitlab-ci.yml
kubextract/templates/_kubepipe-gitlab-ci.yml
kubextract/utils/__init__.py
kubextract/utils/gen_kfserv_conf.py
kubextract/utils/generate.py
kubextract/utils/pipeline.py
kubextract/utils/watcher.py
kubextract/utils-test/__init__.py
kubextract/utils-test/test_kubextract.py
kubextract-1.1.4.dist-info/METADATA
kubextract-1.1.4.dist-info/WHEEL
kubextract-1.1.4.dist-info/entry_points.txt
kubextract-1.1.4.dist-info/top_level.txt
kubextract-1.1.4.dist-info/RECORD
