Metadata-Version: 2.1
Name: kubextract
Version: 1.1.4
Summary: cli framework generator for developing ML on kubeflow
Home-page: UNKNOWN
Author: Bentar Dwika
Author-email: bentar@warungpintar.co
License: UNKNOWN
Platform: UNKNOWN
Requires-Python: >=3.6
Requires-Dist: kubernetes (==11.0.0)
Requires-Dist: ruamel.yaml (==0.16.10)
Requires-Dist: click (==7.1.2)
Requires-Dist: PyInquirer (==1.0.3)
Requires-Dist: prompt-toolkit (==1.0.14)
Requires-Dist: urllib3 (==1.25.9)
Requires-Dist: requests (==2.23.0)
Requires-Dist: kfp (==1.2.0)
